VISA/Automatic_Instrument_Detection.py
VISA/__init__.py
VISA/Quick_Debug/CLI.py
VISA/Quick_Debug/__init__.py
VISA/Source_Measure/__init__.py
VISA/Source_Measure/simple_source_measure.py
mpone/__init__.py
mpone/visa/__init__.py
mpone/visa/manual/__init__.py
mpone/visa/manual/tek_2636B/ConfigPulseIMeasureV.py
mpone/visa/manual/tek_2636B/ConfigPulseIMeasureVSweepLin.py
mpone/visa/manual/tek_2636B/ConfigPulseIMeasureVSweepLog.py
mpone/visa/manual/tek_2636B/ConfigPulseVMeasureI.py
mpone/visa/manual/tek_2636B/ConfigPulseVMeasureISweepLin.py
mpone/visa/manual/tek_2636B/ConfigPulseVMeasureISweepLog.py
mpone/visa/manual/tek_2636B/InitiatePulseTest.py
mpone/visa/manual/tek_2636B/InitiatePulseTestDual.py
mpone/visa/manual/tek_2636B/Os.py
mpone/visa/manual/tek_2636B/Print.py
mpone/visa/manual/tek_2636B/PulseIMeasureV.py
mpone/visa/manual/tek_2636B/PulseVMeasureI.py
mpone/visa/manual/tek_2636B/QueryPulseConfig.py
mpone/visa/manual/tek_2636B/SweepILinMeasureV.py
mpone/visa/manual/tek_2636B/SweepIListMeasureV.py
mpone/visa/manual/tek_2636B/SweepILogMeasureV.py
mpone/visa/manual/tek_2636B/SweepVLinMeasureI.py
mpone/visa/manual/tek_2636B/SweepVListMeasureI.py
mpone/visa/manual/tek_2636B/SweepVLogMeasureI.py
mpone/visa/manual/tek_2636B/__init__.py
mpone/visa/manual/tek_2636B/beeper.py
mpone/visa/manual/tek_2636B/bit.py
mpone/visa/manual/tek_2636B/bufferVar.py
mpone/visa/manual/tek_2636B/dataqueue.py
mpone/visa/manual/tek_2636B/delay.py
mpone/visa/manual/tek_2636B/digio.py
mpone/visa/manual/tek_2636B/display.py
mpone/visa/manual/tek_2636B/errorqueue.py
mpone/visa/manual/tek_2636B/eventlog.py
mpone/visa/manual/tek_2636B/exit.py
mpone/visa/manual/tek_2636B/fileVar_close.py
mpone/visa/manual/tek_2636B/fileVar_flush.py
mpone/visa/manual/tek_2636B/fileVar_read.py
mpone/visa/manual/tek_2636B/fileVar_seek.py
mpone/visa/manual/tek_2636B/fileVar_write.py
mpone/visa/manual/tek_2636B/format.py
mpone/visa/manual/tek_2636B/fs.py
mpone/visa/manual/tek_2636B/gettimezone.py
mpone-0.0.3.dist-info/LICENSE
mpone-0.0.3.dist-info/METADATA
mpone-0.0.3.dist-info/WHEEL
mpone-0.0.3.dist-info/top_level.txt
mpone-0.0.3.dist-info/RECORD
