Metadata-Version: 2.1
Name: mpone
Version: 0.0.3
Summary: MPOne is more than One
Home-page: https://github.com/anine09/MPOne
Author: Epsilon Luoo
Author-email: epsilon_luoo@outlook.com
License: MIT Licence
Keywords: VISA,Material
Platform: any
Requires-Python: >=3.10.0
License-File: LICENSE
Requires-Dist: pyvisa
Requires-Dist: pyvisa-py
Requires-Dist: gpib-ctypes
